temp_converter.py
tempconverter2025-0.3.dist-info/METADATA
tempconverter2025-0.3.dist-info/WHEEL
tempconverter2025-0.3.dist-info/top_level.txt
tempconverter2025-0.3.dist-info/RECORD
